subtune/__init__.py
subtune/cli.py
subtune/config.py
subtune/core/__init__.py
subtune/core/exceptions.py
subtune/core/processor.py
subtune/core/timestamp.py
subtune/core/validator.py
subtune/core/workflow.py
subtune/utils/__init__.py
subtune/utils/backup.py
subtune-1.0.0.dist-info/METADATA
subtune-1.0.0.dist-info/WHEEL
subtune-1.0.0.dist-info/entry_points.txt
subtune-1.0.0.dist-info/licenses/LICENSE
subtune-1.0.0.dist-info/RECORD
