Metadata-Version: 2.4
Name: subtune
Version: 1.0.0
Summary: Tune SRT subtitle timings with ease
Project-URL: Homepage, https://github.com/rafa-garcia/subtune
Project-URL: Repository, https://github.com/rafa-garcia/subtune.git
Project-URL: Issues, https://github.com/rafa-garcia/subtune/issues
Project-URL: Changelog, https://github.com/rafa-garcia/subtune/releases
Author-email: Rafa Garcia <rafa@rafagarcia.info>
Maintainer-email: Rafa Garcia <rafa@rafagarcia.info>
License: MIT
License-File: LICENSE
Keywords: cli,shift,srt,subtitle,sync,timing,video
Classifier: Development Status :: 5 - Production/Stable
Classifier: Environment :: Console
Classifier: Intended Audience :: Developers
Classifier: Intended Audience :: End Users/Desktop
Classifier: License :: OSI Approved :: MIT License
Classifier: Operating System :: OS Independent
Classifier: Programming Language :: Python :: 3
Classifier: Programming Language :: Python :: 3.9
Classifier: Programming Language :: Python :: 3.10
Classifier: Programming Language :: Python :: 3.11
Classifier: Programming Language :: Python :: 3.12
Classifier: Topic :: Multimedia :: Video
Classifier: Topic :: Text Processing :: General
Classifier: Topic :: Utilities
Classifier: Typing :: Typed
Requires-Python: >=3.9
Provides-Extra: build
Requires-Dist: build>=0.10.0; extra == 'build'
Requires-Dist: hatchling>=1.0.0; extra == 'build'
Requires-Dist: twine>=4.0.0; extra == 'build'
Provides-Extra: dev
Requires-Dist: pytest-cov>=4.0.0; extra == 'dev'
Requires-Dist: pytest>=7.0.0; extra == 'dev'
Requires-Dist: ruff>=0.1.0; extra == 'dev'
Provides-Extra: test
Requires-Dist: pytest-cov>=4.0.0; extra == 'test'
Requires-Dist: pytest>=7.0.0; extra == 'test'
